{"posts": [{"author": "hacker333", "timeStamp": "Sun, Dec 11 19:23:58 EST 2016", "subject": "Segfault?", "post": "I am just starting to learn c and I am getting a segfault everytime I run my program. What is that?"}, {"author": "whitehat45", "timeStamp": "Sun, Dec 11 19:39:03 EST 2016", "subject": "Segfault?", "post": "It's most likely just the quality of your code."}, {"author": "yoi5", "timeStamp": "Sun, Dec 11 19:49:06 EST 2016", "subject": "Annoying", "post": "I am sick of this language already!"}, {"author": "me", "timeStamp": "2016-12-12 23:14:28.783631", "subject": "asdadsdas", "post": "asdsd\nsdadssdad\nasdsdasdasda\nadsdasdasdasdad\nasdadasdasdasdasda\nasdasdasadsdasdasdasada\n"}]}